upmcore/__init__.py
upmcore/core/__init__.py
upmcore/core/njs/__init__.py
upmcore/core/python/__init__.py
upmcore/guess/__init__.py
upmcore/index/__init__.py
upmcore/index/njs/__init__.py
upmcore/index/python/__init__.py
upmcore-0.5.dist-info/METADATA
upmcore-0.5.dist-info/WHEEL
upmcore-0.5.dist-info/top_level.txt
upmcore-0.5.dist-info/RECORD
