Metadata-Version: 2.1
Name: upmcore
Version: 0.5
Summary: A universal package manager
Home-page: http://github.com/apollyon9/upm
Author: Apollyon9/Sakurai07
Author-email: blzzardst0rm@gmail.com
License: MIT
Platform: UNKNOWN
